volpy/__init__.py
volpy/volpy.py
votpy/__init__.py
votpy/votpy.py
votpy-0.0.2.dist-info/LICENSE
votpy-0.0.2.dist-info/METADATA
votpy-0.0.2.dist-info/WHEEL
votpy-0.0.2.dist-info/top_level.txt
votpy-0.0.2.dist-info/RECORD
