Metadata-Version: 2.1
Name: votpy
Version: 0.0.2
Summary: Package to calculate Voice Onset Latency
Home-page: https://github.com/adilanchian96/volpy
Author: Andrew Dilanchian
Author-email: adilanchian96@gmail.com
License: UNKNOWN
Project-URL: Bug Tracker, https://github.com/adilanchian96/volpy/issues
Project-URL: Reference 1, https://forum.cogsci.nl/index.php?p=/discussion/1772/
Project-URL: Reference 2, https://stackoverflow.com/questions/18406570/python-record-audio-on-detected-sound
Platform: UNKNOWN
Classifier: Programming Language :: Python :: 3
Classifier: License :: OSI Approved :: MIT License
Classifier: Operating System :: OS Independent
Requires-Python: >=3.7.4
